{
  "$schema": "https://ui.shadcn.com/schema/registry-item.json",
  "name": "chart-group5",
  "title": "Chart-group",
  "description": "A comparison layout with a dual-line chart and summary card showing year-over-year growth.",
  "dependencies": [
    "recharts"
  ],
  "registryDependencies": [
    "utils",
    "card",
    "chart"
  ],
  "files": [
    {
      "path": "block/chart-group5.tsx",
      "content": "\"use client\";\n\nimport { CartesianGrid, Line, LineChart, XAxis, YAxis } from \"recharts\";\n\nimport {\n  Card,\n  CardContent,\n  CardDescription,\n  CardHeader,\n  CardTitle,\n} from \"@/components/ui/card\";\nimport {\n  type ChartConfig,\n  ChartContainer,\n  ChartLegend,\n  ChartLegendContent,\n  ChartTooltip,\n  ChartTooltipContent,\n} from \"@/components/ui/chart\";\nimport { cn } from \"@/lib/utils\";\n\ninterface ChartGroup5Props {\n  className?: string;\n}\n\nconst currentData = [\n  { month: \"Jan\", value: 18600 },\n  { month: \"Feb\", value: 30500 },\n  { month: \"Mar\", value: 23700 },\n  { month: \"Apr\", value: 27300 },\n  { month: \"May\", value: 20900 },\n  { month: \"Jun\", value: 31400 },\n];\n\nconst previousData = [\n  { month: \"Jan\", value: 15200 },\n  { month: \"Feb\", value: 24800 },\n  { month: \"Mar\", value: 21100 },\n  { month: \"Apr\", value: 22500 },\n  { month: \"May\", value: 19400 },\n  { month: \"Jun\", value: 26200 },\n];\n\nconst combinedData = currentData.map((item, index) => ({\n  month: item.month,\n  current: item.value,\n  previous: previousData[index].value,\n}));\n\nconst chartConfig = {\n  current: { label: \"This Year\", color: \"var(--chart-1)\" },\n  previous: { label: \"Last Year\", color: \"var(--chart-4)\" },\n} satisfies ChartConfig;\n\nconst ChartGroup5 = ({ className }: ChartGroup5Props) => {\n  const currentTotal = currentData.reduce((sum, item) => sum + item.value, 0);\n  const previousTotal = previousData.reduce((sum, item) => sum + item.value, 0);\n  const growth = (\n    ((currentTotal - previousTotal) / previousTotal) *\n    100\n  ).toFixed(1);\n\n  return (\n    <section className={cn(\"py-32\", className)}>\n      <div className=\"container grid gap-4 md:grid-cols-3\">\n        <Card className=\"md:col-span-2\">\n          <CardHeader>\n            <CardTitle>Year over Year Comparison</CardTitle>\n            <CardDescription>Revenue performance vs last year</CardDescription>\n          </CardHeader>\n          <CardContent>\n            <ChartContainer config={chartConfig} className=\"h-64 w-full\">\n              <LineChart\n                data={combinedData}\n                margin={{ top: 10, right: 10, left: 0, bottom: 0 }}\n              >\n                <CartesianGrid strokeDasharray=\"3 3\" vertical={false} />\n                <XAxis\n                  dataKey=\"month\"\n                  axisLine={false}\n                  tickLine={false}\n                  tickMargin={8}\n                  fontSize={12}\n                />\n                <YAxis\n                  axisLine={false}\n                  tickLine={false}\n                  tickMargin={8}\n                  fontSize={12}\n                  tickFormatter={(v) => `$${v / 1000}k`}\n                />\n                <ChartTooltip content={<ChartTooltipContent />} />\n                <ChartLegend content={<ChartLegendContent />} />\n                <Line\n                  type=\"monotone\"\n                  dataKey=\"current\"\n                  stroke=\"var(--color-current)\"\n                  strokeWidth={2}\n                  dot={{ fill: \"var(--color-current)\", r: 4 }}\n                />\n                <Line\n                  type=\"monotone\"\n                  dataKey=\"previous\"\n                  stroke=\"var(--color-previous)\"\n                  strokeWidth={2}\n                  strokeDasharray=\"4 4\"\n                  dot={{ fill: \"var(--color-previous)\", r: 4 }}\n                />\n              </LineChart>\n            </ChartContainer>\n          </CardContent>\n        </Card>\n\n        <Card>\n          <CardHeader className=\"pb-3\">\n            <CardTitle>Summary</CardTitle>\n            <CardDescription>Period comparison</CardDescription>\n          </CardHeader>\n          <CardContent className=\"space-y-3 font-mono text-sm\">\n            <div className=\"flex items-center justify-between\">\n              <span className=\"text-muted-foreground\">This Year</span>\n              <span className=\"font-semibold\">\n                ${currentTotal.toLocaleString()}\n              </span>\n            </div>\n            <div className=\"flex items-center justify-between\">\n              <span className=\"text-muted-foreground\">Last Year</span>\n              <span className=\"text-muted-foreground\">\n                ${previousTotal.toLocaleString()}\n              </span>\n            </div>\n            <div className=\"flex items-center justify-between\">\n              <span className=\"text-muted-foreground\">Difference</span>\n              <span className=\"text-green-500\">\n                +${(currentTotal - previousTotal).toLocaleString()}\n              </span>\n            </div>\n            <div className=\"border-t pt-3\">\n              <div className=\"flex items-center justify-between\">\n                <span className=\"text-muted-foreground\">Growth</span>\n                <span className=\"font-semibold text-green-500\">+{growth}%</span>\n              </div>\n            </div>\n            <div className=\"border-t pt-3 text-xs\">\n              <div className=\"flex items-center justify-between\">\n                <span className=\"text-muted-foreground\">Avg/Month (This)</span>\n                <span>${Math.round(currentTotal / 6).toLocaleString()}</span>\n              </div>\n              <div className=\"mt-1 flex items-center justify-between\">\n                <span className=\"text-muted-foreground\">Avg/Month (Last)</span>\n                <span className=\"text-muted-foreground\">\n                  ${Math.round(previousTotal / 6).toLocaleString()}\n                </span>\n              </div>\n            </div>\n          </CardContent>\n        </Card>\n      </div>\n    </section>\n  );\n};\n\nexport { ChartGroup5 };\n",
      "type": "registry:block"
    }
  ],
  "type": "registry:block"
}