{
  "$schema": "https://ui.shadcn.com/schema/registry-item.json",
  "name": "chart-group3",
  "title": "Chart-group",
  "description": "A main chart showing monthly trends with sparkline cards zooming into the last 7 days of key metrics.",
  "dependencies": [
    "lucide-react",
    "recharts"
  ],
  "registryDependencies": [
    "utils",
    "card",
    "chart"
  ],
  "files": [
    {
      "path": "block/chart-group3.tsx",
      "content": "\"use client\";\n\nimport { TrendingDown, TrendingUp } from \"lucide-react\";\nimport {\n  Area,\n  AreaChart,\n  CartesianGrid,\n  Line,\n  LineChart,\n  ResponsiveContainer,\n  XAxis,\n  YAxis,\n} from \"recharts\";\n\nimport {\n  Card,\n  CardContent,\n  CardDescription,\n  CardHeader,\n  CardTitle,\n} from \"@/components/ui/card\";\nimport {\n  type ChartConfig,\n  ChartContainer,\n  ChartTooltip,\n  ChartTooltipContent,\n} from \"@/components/ui/chart\";\nimport { cn } from \"@/lib/utils\";\n\ninterface Stat {\n  title: string;\n  value: string;\n  change: number;\n  sparklineData: { day: string; value: number }[];\n}\n\ninterface ChartGroup3Props {\n  stats?: Stat[];\n  className?: string;\n}\n\nconst defaultStats: Stat[] = [\n  {\n    title: \"Total Revenue\",\n    value: \"$45,231\",\n    change: 20.1,\n    sparklineData: [\n      { day: \"Mon\", value: 6200 },\n      { day: \"Tue\", value: 5800 },\n      { day: \"Wed\", value: 7100 },\n      { day: \"Thu\", value: 6900 },\n      { day: \"Fri\", value: 8200 },\n      { day: \"Sat\", value: 5400 },\n      { day: \"Sun\", value: 5631 },\n    ],\n  },\n  {\n    title: \"Avg Order Value\",\n    value: \"$142\",\n    change: 8.5,\n    sparklineData: [\n      { day: \"Mon\", value: 128 },\n      { day: \"Tue\", value: 135 },\n      { day: \"Wed\", value: 142 },\n      { day: \"Thu\", value: 138 },\n      { day: \"Fri\", value: 155 },\n      { day: \"Sat\", value: 148 },\n      { day: \"Sun\", value: 142 },\n    ],\n  },\n  {\n    title: \"Conversion Rate\",\n    value: \"3.2%\",\n    change: -2.4,\n    sparklineData: [\n      { day: \"Mon\", value: 3.8 },\n      { day: \"Tue\", value: 3.5 },\n      { day: \"Wed\", value: 3.4 },\n      { day: \"Thu\", value: 3.6 },\n      { day: \"Fri\", value: 3.1 },\n      { day: \"Sat\", value: 2.9 },\n      { day: \"Sun\", value: 3.2 },\n    ],\n  },\n];\n\nconst chartData = [\n  { month: \"Jan\", value: 18600 },\n  { month: \"Feb\", value: 30500 },\n  { month: \"Mar\", value: 23700 },\n  { month: \"Apr\", value: 27300 },\n  { month: \"May\", value: 20900 },\n  { month: \"Jun\", value: 31400 },\n];\n\nconst chartConfig = {\n  value: { label: \"Revenue\", color: \"var(--chart-1)\" },\n} satisfies ChartConfig;\n\nconst ChartGroup3 = ({ stats = defaultStats, className }: ChartGroup3Props) => {\n  return (\n    <section className={cn(\"py-32\", className)}>\n      <div className=\"container space-y-4\">\n        <Card>\n          <CardHeader className=\"pb-2\">\n            <CardTitle>Revenue Trend</CardTitle>\n            <CardDescription>Monthly revenue over time</CardDescription>\n          </CardHeader>\n          <CardContent className=\"pb-4\">\n            <ChartContainer config={chartConfig} className=\"h-64 w-full\">\n              <AreaChart\n                data={chartData}\n                margin={{ top: 10, right: 10, left: 0, bottom: 0 }}\n              >\n                <defs>\n                  <linearGradient\n                    id=\"chartGradient3\"\n                    x1=\"0\"\n                    y1=\"0\"\n                    x2=\"0\"\n                    y2=\"1\"\n                  >\n                    <stop\n                      offset=\"0%\"\n                      stopColor=\"var(--color-value)\"\n                      stopOpacity={0.3}\n                    />\n                    <stop\n                      offset=\"100%\"\n                      stopColor=\"var(--color-value)\"\n                      stopOpacity={0}\n                    />\n                  </linearGradient>\n                </defs>\n                <CartesianGrid strokeDasharray=\"3 3\" vertical={false} />\n                <XAxis\n                  dataKey=\"month\"\n                  axisLine={false}\n                  tickLine={false}\n                  tickMargin={8}\n                  fontSize={12}\n                />\n                <YAxis\n                  axisLine={false}\n                  tickLine={false}\n                  tickMargin={8}\n                  fontSize={12}\n                  tickFormatter={(v) => `$${v / 1000}k`}\n                />\n                <ChartTooltip content={<ChartTooltipContent />} />\n                <Area\n                  type=\"monotone\"\n                  dataKey=\"value\"\n                  stroke=\"var(--color-value)\"\n                  strokeWidth={2}\n                  fill=\"url(#chartGradient3)\"\n                />\n              </AreaChart>\n            </ChartContainer>\n          </CardContent>\n        </Card>\n\n        <div className=\"grid gap-4 md:grid-cols-3\">\n          {stats.map((stat, index) => {\n            const isPositive = stat.change >= 0;\n            const sparklineColor = isPositive ? \"#22c55e\" : \"#ef4444\";\n            return (\n              <Card key={index} className=\"overflow-hidden\">\n                <CardHeader className=\"pb-0\">\n                  <CardDescription>Last 7 days</CardDescription>\n                  <div className=\"flex items-center justify-between\">\n                    <CardTitle className=\"text-base\">{stat.title}</CardTitle>\n                    <div className=\"flex items-center gap-2\">\n                      <span className=\"text-2xl font-bold\">{stat.value}</span>\n                      <div className=\"flex items-center gap-1 text-sm\">\n                        {isPositive ? (\n                          <TrendingUp className=\"size-4 text-green-500\" />\n                        ) : (\n                          <TrendingDown className=\"size-4 text-red-500\" />\n                        )}\n                        <span\n                          className={\n                            isPositive ? \"text-green-500\" : \"text-red-500\"\n                          }\n                        >\n                          {isPositive ? \"+\" : \"\"}\n                          {stat.change}%\n                        </span>\n                      </div>\n                    </div>\n                  </div>\n                </CardHeader>\n                <CardContent className=\"pb-0\">\n                  <div className=\"h-16 w-full\">\n                    <ResponsiveContainer width=\"100%\" height=\"100%\">\n                      <LineChart\n                        data={stat.sparklineData}\n                        margin={{ top: 8, right: 0, left: 0, bottom: 0 }}\n                      >\n                        <XAxis\n                          dataKey=\"day\"\n                          axisLine={false}\n                          tickLine={false}\n                          tick={{ fontSize: 10 }}\n                          tickMargin={4}\n                        />\n                        <Line\n                          type=\"monotone\"\n                          dataKey=\"value\"\n                          stroke={sparklineColor}\n                          strokeWidth={2}\n                          dot={false}\n                        />\n                      </LineChart>\n                    </ResponsiveContainer>\n                  </div>\n                </CardContent>\n              </Card>\n            );\n          })}\n        </div>\n      </div>\n    </section>\n  );\n};\n\nexport { ChartGroup3 };\n",
      "type": "registry:block"
    }
  ],
  "type": "registry:block"
}